{
	"configurations" : 
	[
		{
			"directories" : 
			[
				{
					"build" : ".",
					"jsonFile" : "directory-.-Debug-d0094a50bb2071803777.json",
					"minimumCMakeVersion" : 
					{
						"string" : "3.26"
					},
					"projectIndex" : 0,
					"source" : ".",
					"targetIndexes" : 
					[
						0,
						1,
						2,
						3,
						4,
						5,
						6,
						7,
						8,
						9,
						10
					]
				}
			],
			"name" : "Debug",
			"projects" : 
			[
				{
					"directoryIndexes" : 
					[
						0
					],
					"name" : "c__assignment",
					"targetIndexes" : 
					[
						0,
						1,
						2,
						3,
						4,
						5,
						6,
						7,
						8,
						9,
						10
					]
				}
			],
			"targets" : 
			[
				{
					"directoryIndex" : 0,
					"id" : ".1::@6890427a1f51a3e7e1df",
					"jsonFile" : "target-.1-Debug-ea31f517696cb9197db0.json",
					"name" : ".1",
					"projectIndex" : 0
				},
				{
					"directoryIndex" : 0,
					"id" : ".6::@6890427a1f51a3e7e1df",
					"jsonFile" : "target-.6-Debug-82c449affed22767e7ef.json",
					"name" : ".6",
					"projectIndex" : 0
				},
				{
					"directoryIndex" : 0,
					"id" : "10::@6890427a1f51a3e7e1df",
					"jsonFile" : "target-10-Debug-4347e28b059ae75a5d2d.json",
					"name" : "10",
					"projectIndex" : 0
				},
				{
					"directoryIndex" : 0,
					"id" : "11::@6890427a1f51a3e7e1df",
					"jsonFile" : "target-11-Debug-6871e9aaa331d4b73c22.json",
					"name" : "11",
					"projectIndex" : 0
				},
				{
					"directoryIndex" : 0,
					"id" : "2::@6890427a1f51a3e7e1df",
					"jsonFile" : "target-2-Debug-227ef9ebcf759b22f516.json",
					"name" : "2",
					"projectIndex" : 0
				},
				{
					"directoryIndex" : 0,
					"id" : "3::@6890427a1f51a3e7e1df",
					"jsonFile" : "target-3-Debug-624c66102ee28d256092.json",
					"name" : "3",
					"projectIndex" : 0
				},
				{
					"directoryIndex" : 0,
					"id" : "4::@6890427a1f51a3e7e1df",
					"jsonFile" : "target-4-Debug-6b4229aa66b0863f0860.json",
					"name" : "4",
					"projectIndex" : 0
				},
				{
					"directoryIndex" : 0,
					"id" : "5::@6890427a1f51a3e7e1df",
					"jsonFile" : "target-5-Debug-2a2e2d4ccc1f8ccf0e2a.json",
					"name" : "5",
					"projectIndex" : 0
				},
				{
					"directoryIndex" : 0,
					"id" : "7::@6890427a1f51a3e7e1df",
					"jsonFile" : "target-7-Debug-55f839c8c513e6dce074.json",
					"name" : "7",
					"projectIndex" : 0
				},
				{
					"directoryIndex" : 0,
					"id" : "8::@6890427a1f51a3e7e1df",
					"jsonFile" : "target-8-Debug-aeb109a715abe6c2f2f5.json",
					"name" : "8",
					"projectIndex" : 0
				},
				{
					"directoryIndex" : 0,
					"id" : "9::@6890427a1f51a3e7e1df",
					"jsonFile" : "target-9-Debug-5ec3d64cab0f63ccee77.json",
					"name" : "9",
					"projectIndex" : 0
				}
			]
		}
	],
	"kind" : "codemodel",
	"paths" : 
	{
		"build" : "C:/Users/Admin/Documents/GitHub/c--assignment/cmake-build-debug",
		"source" : "C:/Users/Admin/Documents/GitHub/c--assignment"
	},
	"version" : 
	{
		"major" : 2,
		"minor" : 5
	}
}
